torch_cubic_b_spline_grid/__init__.py
torch_cubic_b_spline_grid/constants.py
torch_cubic_b_spline_grid/grids.py
torch_cubic_b_spline_grid/interpolate_grids.py
torch_cubic_b_spline_grid/interpolate_pieces.py
torch_cubic_b_spline_grid/pad_grids.py
torch_cubic_b_spline_grid/utils.py
torch_cubic_b_spline_grid-0.0.2.dist-info/METADATA
torch_cubic_b_spline_grid-0.0.2.dist-info/WHEEL
torch_cubic_b_spline_grid-0.0.2.dist-info/licenses/LICENSE
torch_cubic_b_spline_grid-0.0.2.dist-info/RECORD
