Metadata-Version: 2.1
Name: torch-cubic-b-spline-grid
Version: 0.0.2
Summary: Cubic B-spline interpolation on multidimensional grids in PyTorch
Project-URL: homepage, https://github.com/alisterburt/torch-cubic-b-spline-grid
Project-URL: repository, https://github.com/alisterburt/torch-cubic-b-spline-grid
Author: Alister Burt
Author-email: alisterburt@gmail.com
License: BSD 3-Clause License
License-File: LICENSE
Classifier: Development Status :: 3 - Alpha
Classifier: License :: OSI Approved :: BSD License
Classifier: Programming Language :: Python :: 3
Classifier: Programming Language :: Python :: 3.8
Classifier: Programming Language :: Python :: 3.9
Classifier: Programming Language :: Python :: 3.10
Requires-Python: >=3.8
Requires-Dist: einops
Requires-Dist: numpy
Requires-Dist: torch
Requires-Dist: typing-extensions
Provides-Extra: dev
Requires-Dist: black; extra == 'dev'
Requires-Dist: ipython; extra == 'dev'
Requires-Dist: mypy; extra == 'dev'
Requires-Dist: pdbpp; extra == 'dev'
Requires-Dist: pre-commit; extra == 'dev'
Requires-Dist: pytest; extra == 'dev'
Requires-Dist: pytest-cov; extra == 'dev'
Requires-Dist: rich; extra == 'dev'
Requires-Dist: ruff; extra == 'dev'
Provides-Extra: test
Requires-Dist: pytest-cov; extra == 'test'
Requires-Dist: pytest>=6.0; extra == 'test'
